arblay/__init__.py
arblay/make_arbitrary_layout_fig.py
arblay-1.0.dist-info/LICENSE
arblay-1.0.dist-info/METADATA
arblay-1.0.dist-info/WHEEL
arblay-1.0.dist-info/top_level.txt
arblay-1.0.dist-info/RECORD
