Metadata-Version: 2.1
Name: arblay
Version: 1.0
Summary: Making the matplotlib figures with an arbitrary layout specifying pixels
Home-page: https://github.com/YoshikiKubotani/arbitrary_mpl_figures
Download-URL: https://github.com/YoshikiKubotani/arbitrary_mpl_figures
Author: Yoshiki Kubotani
Author-email: yoshikikubotani.lab@gmail.com
Maintainer: Yoshiki Kubotani
Maintainer-email: yoshikikubotani.lab@gmail.com
License: MIT
Classifier: Intended Audience :: Science/Research
Classifier: License :: OSI Approved :: MIT License
Classifier: Programming Language :: Python :: 3
Classifier: Programming Language :: Python :: 3.7
Classifier: Programming Language :: Python :: 3.8
Classifier: Programming Language :: Python :: 3.9
Classifier: Programming Language :: Python :: 3 :: Only
Classifier: Topic :: Scientific/Engineering
Classifier: Topic :: Scientific/Engineering :: Visualization
Classifier: Topic :: Scientific/Engineering :: Artificial Intelligence
Classifier: Topic :: Multimedia :: Graphics
Classifier: Framework :: Matplotlib
Requires-Python: >=3.7
License-File: LICENSE
Requires-Dist: numpy (>=1.20)
Requires-Dist: matplotlib (>=3.0)
